<?xml version="1.0" encoding="UTF-8"?>
<!-- 关卡设定-->
  <Story>
<time>第三天</time>
  <place>酒桌</place>
  <image_name>2.jpg</image_name>
 <elem>
    <name></name>
    <answer>看到之前的老板下台之后，我的内心着实松了一口气。这一个月来一直提心吊胆的，终于也可以把心放回到肚子里了。</answer>
  </elem>
  <elem>
    <name>我</name>
    <answer>我戳戳兰兰：“下班一起去吃点好吃的吧，我请客。”</answer>
  </elem>
  <elem>
    <name></name>
    <answer>兰兰疑惑：“你干嘛突然这么大方！”</answer>
  </elem>
  <elem>
    <name>我</name>
    <answer>“你也知道，庆祝那个性骚扰狂魔的下台啊！”</answer>
  </elem>
  <elem>
    <name>兰兰</name>
    <answer>兰兰立刻了然于胸：“你的确该庆祝庆祝！差一点你就成了老板的小蜜了！”</answer>
  </elem>
  <elem>
    <name>我</name>
    <answer>“闭嘴吧你！我们去吃啥呢？”</answer>
  </elem>
  <elem>
    <name>兰兰</name>
    <answer>“我们去撸串啊，我最近找到一家超好吃的烧烤摊！”</answer>
  </elem>
  <elem>
    <name></name>
    <answer>我想了想，自从大学毕业后，一直都是一个人独来独往的，的确很久都没有吃过烧烤了。毕竟烧烤要和朋友一起吃才过瘾嘛。</answer>
  </elem>
  <elem>
    <name>兰兰</name>
    <answer>“那家烧烤店晚上七点才出摊，我们下班之后稍微逛逛再过去，估计正好可以吃。”</answer>
  </elem>
  <elem>
    <name>我</name>
    <answer>“好呀！”</answer>
  </elem>
  <elem>
    <name></name>
    <answer>好不容易挨到下班，我和兰兰立刻同步的收拾东西准备走。</answer>
  </elem>
  <elem>
    <name>兰兰</name>
    <answer>“你看，新来的那个海归还在办公室呢，我们就这样走真的好吗？”</answer>
  </elem>
  <elem>
    <name>我</name>
    <answer>“有什么关系啊？下班时间到了呀。”</answer>
  </elem>
  <elem>
    <name>兰兰</name>
    <answer>兰兰做害羞状：“人家想给他留下一个好印象嘛~”</answer>
  </elem>
  <elem>
    <name>我</name>
    <answer>我呕吐：“快得了吧你，你就算天天加班到十点他也不会因为这个爱上你的。”</answer>
  </elem>
</Story>