<?xml version="1.0" encoding="UTF-8"?>
<!-- 关卡设定-->
  <Story>
<time>第三天</time>
  <place>酒桌</place>
  <image_name>2.jpg</image_name>
<!--体检剧情 -->
  <elem>
    <name></name>
    <answer>最近这些天，我老是感到一阵阵的晕眩，好几次都差点晕过去。</answer>
  </elem>
  <elem>
    <name>我</name>
    <answer>“奇怪，我这是怎么了……”又一次眼前发黑，我好不容易稳住了身体，忍不住担心着。</answer>
  </elem>
  <elem>
    <name></name>
    <answer>我怀疑自己可能是太累了。但是没办法，该干的活还是得干呀。</answer>
  </elem>
  <elem>
    <name></name>
    <answer>又是一天加班到深夜。我饿的胃一阵一阵的刺痛。</answer>
  </elem>
  <elem>
    <name>我</name>
    <answer>“唔……”好痛啊，我捂着肚子，冷汗留了下来。</answer>
  </elem>
  <elem>
    <name></name>
    <answer>但我感觉到，除了胃痛，我的胸也很闷，呼吸不上来。背部也传来一阵阵的隐痛。</answer>
  </elem>
  <elem>
    <name>我</name>
    <answer>“等忙完这一段，真得上医院做个检查才行了。”我心里下了决心。</answer>
  </elem>
  <elem>
    <name></name>
    <answer>但手头的工作不能不做，我强迫自己忽略掉这些感觉，继续埋头苦干着。</answer>
  </elem>
  <elem>
    <name>我</name>
    <answer>“啊……终于搞定了。”我关掉了电脑。</answer>
  </elem>
  <elem>
    <name></name>
    <answer>正打算站起来时，胸前一阵疼痛，心脏剧烈的跳动着。</answer>
  </elem>
  <elem>
    <name>我</name>
    <answer>“唔……”我捂着胸口，站也站不稳，只能蹲了下去。</answer>
  </elem>
  <elem>
    <name></name>
    <answer>突然我感到呼吸不过来，就像一只大手卡住了我的脖子，伴随着更加剧烈地仿佛要从我胸腔中蹦出来的心跳，我眼前一黑，重重的倒了下去，失去了知觉。</answer>
  </elem>
  <elem>
    <name></name>
    <answer>第二天。</answer>
  </elem>
  <elem>
    <name>？？？</name>
    <answer>“啊————”一声女性的尖叫声从办公大楼内传出。</answer>
  </elem>
  <elem>
    <name></name>
    <answer>第一个来到办公室的是会计，一个年轻的女孩，她推开门就发现了我倒在办公室里，不过经过了一夜，我早已没有了呼吸。</answer>
  </elem>
  <elem>
    <name></name>
    <answer>警车和救护车很快来了，经鉴定，我是由心脏性猝死导致的死亡，属于意外。当天警察就通知了我的家人，他们很快来了，对着医院里蒙着白布的我的尸体，二老们再也抑制不住悲伤，互相搀扶着痛哭出声。</answer>
  </elem>
  <elem>
    <name></name>
    <answer>而这些，我再也看不到了……</answer>
  </elem>
  <elem>
    <name></name>
    <answer>【Bad End：病死】</answer>
  </elem>
</Story>