<?xml version="1.0" encoding="UTF-8"?>
<!-- 关卡设定-->
  <Story>
<time>第三天</time>
  <place>酒桌</place>
  <image_name>4_1.jpg</image_name>
  <elem>
    <name>同事</name>
    <answer>“哎！找个人送你回家吧！”</answer>
  </elem>
  <elem>
    <name>我</name>
    <answer>“不用了不用了！”我回头喊了一声，出门拦了辆出租车，离开了。</answer>
  </elem>
  <elem>
    <name></name>
    <answer>刚才，那就是性骚扰吧？而且还提出要包养我？开玩笑吗！老板上下其手的动作似乎还残留在身上让人恶心，还有那轻佻的眼神，都让人觉得鸡皮疙瘩起了一身……</answer>
  </elem>
  <elem>
    <name></name>
    <answer>真没想到，这样的事会出现在我的身上，接下来，我该如何面对老板，如何面对工作……喝完酒后涨涨的脑袋此刻越发的不清醒，我感到头痛。</answer>
  </elem>
  <elem>
    <name></name>
    <answer>而且，这次的我选择忍耐，老板是不是会觉得我是默认了，从而更加变本加厉？我的头更痛了。</answer>
  </elem>
</Story>